exact/__init__.py
exact/admin.py
exact/api.py
exact/app.py
exact/models.py
exact/signals.py
exact/storage.py
exact/urls.py
exact/views.py
exact/migrations/0001_initial.py
exact/migrations/0002_remove_session_division.py
exact/migrations/__init__.py
exact/templates/exact/status.html
django_exact-0.6.0.dist-info/LICENSE.txt
django_exact-0.6.0.dist-info/METADATA
django_exact-0.6.0.dist-info/WHEEL
django_exact-0.6.0.dist-info/top_level.txt
django_exact-0.6.0.dist-info/RECORD
