Metadata-Version: 2.1
Name: django-exact
Version: 0.6.0
Summary: API Wrapper and Django app for Exact Online
Home-page: https://github.com/affiliprint/django-exact
Author: Malte Böhme, Affiliprint Deutschland GmbH
Author-email: malte.boehme@affiliprint.com
License: MIT
License-File: LICENSE.txt
Requires-Dist: Django
Requires-Dist: requests
Requires-Dist: urllib3
